MANIFEST.in
README.md
setup.py
examples/Python/__init__.py
examples/Python/snowboydecoder.py
examples/Python/snowboydetect.py
include/snowboy-detect.h
lib/aarch64-ubuntu1604/libsnowboy-detect.a
lib/edison/libsnowboy-detect.a
lib/fedora25-armv7/libsnowboy-detect.a
lib/node/SnowboyDetectNative.d.ts
lib/node/index.ts
lib/node/node-pre-gyp.d.ts
lib/osx/libsnowboy-detect.a
lib/pine64/libsnowboy-detect.a
lib/rpi/libsnowboy-detect.a
lib/ubuntu64/libsnowboy-detect.a
resources/alexa.umdl
resources/common.res
resources/ding.wav
resources/dong.wav
resources/snowboy.umdl
resources/snowboy.wav
snowboy.egg-info/PKG-INFO
snowboy.egg-info/SOURCES.txt
snowboy.egg-info/dependency_links.txt
snowboy.egg-info/not-zip-safe
snowboy.egg-info/requires.txt
snowboy.egg-info/top_level.txt
swig/Python/Makefile
swig/Python/snowboy-detect-swig.cc
swig/Python/snowboy-detect-swig.i
swig/Python/snowboy-detect-swig.o
swig/Python/snowboydetect.py