Metadata-Version: 1.0
Name: snowboy
Version: 1.2.0b1
Summary: Snowboy is a customizable hotword detection engine
Home-page: https://snowboy.kitt.ai
Author: KITT.AI
Author-email: snowboy@kitt.ai
License: Apache-2.0
Platform: UNKNOWN
